replicateETF/__init__.py
replicateETF/scrapeETF.py
replicateETF-0.0.16.dist-info/LICENSE
replicateETF-0.0.16.dist-info/METADATA
replicateETF-0.0.16.dist-info/WHEEL
replicateETF-0.0.16.dist-info/top_level.txt
replicateETF-0.0.16.dist-info/RECORD
