Metadata-Version: 2.1
Name: replicateETF
Version: 0.0.16
Summary: A package that replicates an ETFs by buying the underlying assets
Home-page: https://github.com/pypa/replicateETF
Author: Arshya Ary Sharifian
Author-email: arshyasharifian@gmail.com
License: UNKNOWN
Platform: UNKNOWN
Classifier: Programming Language :: Python :: 3
Classifier: License :: OSI Approved :: MIT License
Classifier: Operating System :: OS Independent
Requires-Python: >=3.6
License-File: LICENSE
Requires-Dist: beautifulsoup4 (>=4.11.1)
Requires-Dist: alpaca-trade-api (>=2.0.0)
Requires-Dist: selenium (>=4.1.3)
